{
  "bittensor_id": "",
  "name": "Identity Verification Protocol",
  "github": ["https://github.com/TatsuProject/Identity-Subnet"],
  "hw_requirements": "",
  "image_url": "",
  "description": "The Taτsu Identity Subnet aims to calculate a human score based on various metrics such as GitHub account, TAO balance, Social Media and other relevant data points. The project involves validators and miners working together to compute and verify these scores.",
  "bittensor_discord_id": "",
  "team": "DAASI",
  "summary": "",
  "websites": []
}
